wemopy/__init__.py
wemopy/types.py
wemopy/wemopy.py
wemopy/internal/__init__.py
wemopy/internal/rules_pb2.py
wemopy/internal/rules_pb2_grpc.py
wemopy-0.3.1.dist-info/AUTHORS.rst
wemopy-0.3.1.dist-info/LICENSE
wemopy-0.3.1.dist-info/METADATA
wemopy-0.3.1.dist-info/WHEEL
wemopy-0.3.1.dist-info/top_level.txt
wemopy-0.3.1.dist-info/RECORD
